{
  "captured_at": "2026-04-10T03:27:14.773309+00:00",
  "current_pid": 97153,
  "memory_pressure": {
    "returncode": 0,
    "head": [
      "The system has 549755813888 (33554432 pages with a page size of 16384).",
      "",
      "Stats: ",
      "Pages free: 12343267 ",
      "Pages purgeable: 46488 ",
      "Pages purged: 2803006 ",
      "",
      "Swap I/O:",
      "Swapins: 0 ",
      "Swapouts: 0 ",
      "",
      "Page Q counts:",
      "Pages active: 2824474 ",
      "Pages inactive: 5233465 ",
      "Pages speculative: 142395 ",
      "Pages throttled: 0 ",
      "Pages wired down: 12781257 ",
      "",
      "Compressor Stats:",
      "Pages used by compressor: 152653 "
    ],
    "system_free_percent": 61
  },
  "gpu_snapshot": {
    "returncode": 0,
    "head": [
      "+-o AGXAcceleratorG15X  <class AGXAcceleratorG15X, id 0x1000005f2, registered, matched, active, busy 0 (23513 ms), retain 70>",
      "    {",
      "      \"SchedulerState\" = {\"Stamps\"=({\"idx\"=38,\"sub\"=1773455872,\"gpu\"=1773453056},{\"idx\"=77,\"sub\"=244676352,\"gpu\"=244673536},{\"idx\"=122,\"sub\"=390419968,\"gpu\"=390417152}),\"BusyWorkQueues\"=({\"submitted\"=10459570,\"id\"=83,\"added\"=10459570,\"finished\"=10459559,\"state\"=\"Idle\",\"submit\"=(524376427520)},{\"submitted\"=6875335,\"id\"=68,\"added\"=6875335,\"finished\"=6875324,\"state\"=\"Idle\",\"submit\"=(164982210560)},{\"submitted\"=955451,\"id\"=42,\"added\"=955451,\"finished\"=955440,\"state\"=\"Idle\",\"submit\"=(330957155584)})}",
      "      \"IOMatchedAtBoot\" = Yes",
      "      \"vendor-id\" = <6b100000>",
      "      \"GPURawCounterBundleName\" = \"AGXGPURawCounterBundle\"",
      "      \"AGXParameterBufferMaxSizeEverMemless\" = 1148715008",
      "      \"GPURawCounterPluginClassName\" = \"AGXGPURawCounterSourceGroup\"",
      "      \"MetalPluginClassName\" = \"AGXG15DDevice\"",
      "      \"SCMVersionNumber\" = \"\"",
      "      \"AGCInfo\" = {\"fLastSubmissionPID\"=53429,\"fSubmissionsSinceLastCheck\"=0,\"fBusyCount\"=0}",
      "      \"CommandSubmissionEnabled\" = Yes",
      "      \"IONameMatched\" = \"gpu,t6032\"",
      "      \"MetalPluginName\" = \"AGXMetalG15X_M2\"",
      "      \"PerformanceStatistics\" = {\"In use system memory (driver)\"=0,\"Alloc system memory\"=204013289472,\"Tiler Utilization %\"=100,\"recoveryCount\"=0,\"lastRecoveryTime\"=0,\"Renderer Utilization %\"=100,\"TiledSceneBytes\"=3473408,\"Device Utilization %\"=100,\"SplitSceneCount\"=0,\"Allocated PB Size\"=280231936,\"In use system memory\"=200879112192}",
      "      \"IOGLBundleName\" = \"AppleMetalOpenGLRenderer\"",
      "      \"AGXParameterBufferMaxSizeNeverMemless\" = 574357504",
      "      \"IOGLESBundleName\" = \"AppleMetalGLRenderer\"",
      "      \"IOSourceVersion\" = \"350.38\"",
      "      \"IOPersonalityPublisher\" = \"com.apple.AGXG15C\""
    ],
    "device_util_percent": 100,
    "renderer_util_percent": 100,
    "tiler_util_percent": 100,
    "alloc_system_memory_bytes": 204013289472,
    "in_use_system_memory_bytes": 200879112192
  },
  "competing_mlx_train_processes": []
}